archive_toolbox/__init__.py
archive_toolbox/logic.py
archive_toolbox/main.py
archive_toolbox/utils.py
archive_toolbox-1.0.dist-info/LICENSE
archive_toolbox-1.0.dist-info/METADATA
archive_toolbox-1.0.dist-info/WHEEL
archive_toolbox-1.0.dist-info/entry_points.txt
archive_toolbox-1.0.dist-info/top_level.txt
archive_toolbox-1.0.dist-info/RECORD
