Metadata-Version: 2.1
Name: archive_toolbox
Version: 1.0
Summary: A toolbox for managing archives
Home-page: https://github.com/idmaksim/archive_toolbox
Author: Dementev Maksim
Author-email: i@dmaksim.ru
Classifier: Programming Language :: Python :: 3
Classifier: License :: OSI Approved :: MIT License
Classifier: Operating System :: OS Independent
Requires-Python: >=3.6
License-File: LICENSE
Requires-Dist: pyfiglet ==1.0.2
